<annotations><filename>00000486.JPEG</filename><folder>images</folder><size><width>1000</width><height>1000</height><depth>3</depth></size><object><name>christmas tree</name><pose>Unspecified</pose><truncated>0</truncated><difficult>0</difficult><bndbox><xmin>138.0</xmin><ymin>198.0</ymin><xmax>455.0</xmax><ymax>863.0</ymax></bndbox></object><object><name>christmas tree</name><pose>Unspecified</pose><truncated>0</truncated><difficult>0</difficult><bndbox><xmin>377.0</xmin><ymin>109.00000000000006</ymin><xmax>658.0</xmax><ymax>714.0</ymax></bndbox></object><object><name>christmas tree</name><pose>Unspecified</pose><truncated>0</truncated><difficult>0</difficult><bndbox><xmin>622.0000000000001</xmin><ymin>228.0</ymin><xmax>897.0000000000001</xmax><ymax>792.0</ymax></bndbox></object></annotations>